.gitignore
.python-version
LICENSE
PKG-INFO
README.md
__init__.py
attention.py
pyproject.toml
transformer_flow.py
uv.lock
assets/cifar10_warp.gif
assets/mnist_warp.gif
tarflows/.gitignore
tarflows/CACHEDIR.TAG
tarflows/pyvenv.cfg
tarflows/bin/activate
tarflows/bin/activate.bat
tarflows/bin/activate.csh
tarflows/bin/activate.fish
tarflows/bin/activate.nu
tarflows/bin/activate.ps1
tarflows/bin/activate_this.py
tarflows/bin/deactivate.bat
tarflows/bin/pydoc.bat
tarflows/bin/python
tarflows/bin/python3
tarflows/bin/python3.11
tarflows/lib/python3.11/site-packages/_virtualenv.pth
tarflows/lib/python3.11/site-packages/_virtualenv.py
transformer_flow-0.0.0.dist-info/METADATA
transformer_flow-0.0.0.dist-info/WHEEL
transformer_flow-0.0.0.dist-info/licenses/LICENSE
transformer_flow-0.0.0.dist-info/RECORD
