Metadata-Version: 2.4
Name: transformer_flow
Version: 0.0.0
Summary: Implementation of Apple ML's TARFlow in JAX.
Author-email: Jed Homer <jedhmr@gmail.com>
License: MIT License
License-File: LICENSE
Keywords: deep-learning,generative-models,jax,machine-learning,normalizing-flows
Classifier: Development Status :: 3 - Alpha
Classifier: Intended Audience :: Science/Research
Classifier: License :: OSI Approved :: MIT License
Classifier: Natural Language :: English
Classifier: Programming Language :: Python :: 3
Classifier: Topic :: Scientific/Engineering :: Artificial Intelligence
Requires-Python: >=3.10
Requires-Dist: beartype
Requires-Dist: datasets
Requires-Dist: einops
Requires-Dist: equinox
Requires-Dist: ipykernel>=6.29.5
Requires-Dist: jax
Requires-Dist: jaxtyping
Requires-Dist: matplotlib
Requires-Dist: ml-collections
Requires-Dist: optax
Requires-Dist: pip>=25.1.1
Requires-Dist: tqdm
